colinote/__init__.py
colinote/cli.py
colinote/data_types.py
colinote/utils.py
tests/__init__.py
tests/test_colinote.py
tests/test_utils.py
colinote-0.1.0.dist-info/LICENSE
colinote-0.1.0.dist-info/METADATA
colinote-0.1.0.dist-info/WHEEL
colinote-0.1.0.dist-info/entry_points.txt
colinote-0.1.0.dist-info/top_level.txt
colinote-0.1.0.dist-info/RECORD
