Metadata-Version: 2.1
Name: colinote
Version: 0.1.0
Summary: A CLI note-taking application
Home-page: https://github.com/tiakas/colinote
Author: Giannis Tiakas
Author-email: giannis@tiakas.com
Keywords: cli,note-taking
Classifier: Development Status :: 3 - Alpha
Classifier: Intended Audience :: End Users/Desktop
Classifier: Topic :: Utilities
Classifier: License :: OSI Approved :: MIT License
Classifier: Programming Language :: Python :: 3
Requires-Python: >=3.6
License-File: LICENSE
Requires-Dist: click (==8.0.1)
Requires-Dist: rich (==10.9.0)
Requires-Dist: pyyaml (==5.4.1)
